gwmemory/__init__.py
gwmemory/angles.py
gwmemory/gwmemory.py
gwmemory/harmonics.py
gwmemory/qnms.py
gwmemory/utils.py
gwmemory/waveforms.py
gwmemory/data/fitcoeffsWEB.dat
gwmemory/data/gamma_coefficients_delta_m_-1.dat
gwmemory/data/gamma_coefficients_delta_m_-2.dat
gwmemory/data/gamma_coefficients_delta_m_-3.dat
gwmemory/data/gamma_coefficients_delta_m_-4.dat
gwmemory/data/gamma_coefficients_delta_m_-5.dat
gwmemory/data/gamma_coefficients_delta_m_-6.dat
gwmemory/data/gamma_coefficients_delta_m_-7.dat
gwmemory/data/gamma_coefficients_delta_m_-8.dat
gwmemory/data/gamma_coefficients_delta_m_0.dat
gwmemory/data/gamma_coefficients_delta_m_1.dat
gwmemory/data/gamma_coefficients_delta_m_2.dat
gwmemory/data/gamma_coefficients_delta_m_3.dat
gwmemory/data/gamma_coefficients_delta_m_4.dat
gwmemory/data/gamma_coefficients_delta_m_5.dat
gwmemory/data/gamma_coefficients_delta_m_6.dat
gwmemory/data/gamma_coefficients_delta_m_7.dat
gwmemory/data/gamma_coefficients_delta_m_8.dat
gwmemoritz-0.1.3.dist-info/LICENSE
gwmemoritz-0.1.3.dist-info/METADATA
gwmemoritz-0.1.3.dist-info/WHEEL
gwmemoritz-0.1.3.dist-info/top_level.txt
gwmemoritz-0.1.3.dist-info/RECORD
