Metadata-Version: 2.1
Name: gwmemoritz
Version: 0.1.3
Summary: UNKNOWN
Home-page: UNKNOWN
Author: UNKNOWN
Author-email: UNKNOWN
License: UNKNOWN
Platform: UNKNOWN
Requires-Dist: numpy
Requires-Dist: scipy
Requires-Dist: pandas
Requires-Dist: glob2
Requires-Dist: deepdish
Requires-Dist: lalsuite
